{
  "resources": {
    "body": [
      {
        "type": "style",
        "src": "./build/app.css"
      },
      {
        "type": "script",
        "src": "./build/app.js"
      }
    ]
  },
  "preview": {
    "handlers": [
      {
        "options": ["*"],
        "execute": "INSTALL_SCOPE.setOptions(INSTALL_OPTIONS)"
      }
    ]
  },
  "options": {
    "properties": {
      "location": {
        "title": "Summary location",
        "description": "Where should the summary appear on the page?",
        "order": 1,
        "type": "object",
        "format": "element",
        "default": {
          "selector": "body",
          "method": "prepend"
        }
      },
      "image": {
        "order": 2,
        "title": "select your image",
        "type": "string",
        "format": "image",
        "default": "http://madeworthy.com/wp-content/uploads/2015/01/gravatar-logo-512.jpg"
      },
      "messageTitle": {
        "order": 3,
        "title": "Message Title",
        "type": "string",
        "default": "Hello!"
      },
      "message": {
        "order": 4,
        "title": "Message",
        "type": "string",
        "default": "This is my webpage!"
      },
      "email": {
        "order": 5,
        "title": "Email",
        "type": "string",
        "default": "your@email.com"
      },
      "twitter": {
        "order": 6,
        "title": "Twitter",
        "type": "string",
        "default": "twitter.com"
      },
      "facebook": {
        "order": 7,
        "title": "Facebook",
        "type": "string",
        "default": "facebook.com"
      },
      "linkedIn": {
        "order": 8,
        "title": "LinkedIn",
        "type": "string",
        "default": "linkedIn.com"
      }
    }
  }
}
